easync/__init__.py
easync/promise2.py
easync/promise3.py
easync/supports.py
easync-1.2.0b2.dist-info/DESCRIPTION.rst
easync-1.2.0b2.dist-info/METADATA
easync-1.2.0b2.dist-info/RECORD
easync-1.2.0b2.dist-info/WHEEL
easync-1.2.0b2.dist-info/metadata.json
easync-1.2.0b2.dist-info/top_level.txt
